{
  "id": 254,
  "name": "sceptile",
  "types": [
    "grass"
  ],
  "baseStats": {
    "hp": 70,
    "attack": 85,
    "defense": 65,
    "specialAttack": 105,
    "specialDefense": 85,
    "speed": 120
  },
  "spriteUrl": "/sprites/254.png",
  "moves": [
    "hyper-beam",
    "focus-punch",
    "frenzy-plant",
    "giga-impact",
    "leaf-storm",
    "solar-blade",
    "double-edge",
    "solar-beam",
    "outrage",
    "focus-blast",
    "earthquake",
    "take-down",
    "leaf-blade",
    "energy-ball",
    "body-slam",
    "dragon-pulse",
    "slam",
    "dig",
    "crunch",
    "dragon-claw",
    "seed-bomb",
    "x-scissor",
    "grass-pledge",
    "throat-chop",
    "tera-blast",
    "thunder-punch",
    "rock-slide",
    "giga-drain",
    "brick-break",
    "drain-punch",
    "slash",
    "facade",
    "night-slash",
    "low-sweep",
    "upper-hand",
    "swift",
    "thief",
    "dragon-breath",
    "rock-tomb",
    "aerial-ace",
    "magical-leaf",
    "assurance",
    "bulldoze",
    "dragon-tail",
    "breaking-swipe",
    "acrobatics",
    "grassy-glide",
    "trailblaze",
    "pound",
    "giga-drain",
    "quick-attack",
    "false-swipe",
    "fury-cutter",
    "vacuum-wave",
    "leafage",
    "double-kick",
    "bullet-seed",
    "scale-shot",
    "absorb",
    "swords-dance",
    "leer",
    "agility",
    "protect",
    "dragon-dance"
  ],
  "abilities": [
    "overgrow",
    "unburden"
  ]
}